{
  "generated_at": "2026-04-02T23:57:02+09:00",
  "mode": "single_analysis",
  "code": "9101",
  "company_name": "日本郵船",
  "base_price": 5011,
  "html_url": "https://k84ht2.github.io/stock-report/single/analysis_9101.html",
  "json_url": "https://k84ht2.github.io/stock-report/single/analysis_9101.json",
  "meta_ok": true,
  "meta_error": null,
  "item": {
    "code": "9101",
    "company_name": "日本郵船",
    "type": "hold",
    "price_now": 6162,
    "prev_close": 5984,
    "change_day": 0.0297,
    "change_intraday": null,
    "close_latest": 6162,
    "sma5": 5906.2,
    "sma25": 5717.12,
    "sma75": 5294.75,
    "sma200": 5212.12,
    "sma25_slope": 36.56,
    "sma75_slope": 17.507,
    "rsi14": 65.91,
    "atr14": 200.19,
    "atr14_pct": 0.0335,
    "abnormal_move": false,
    "trend_strength": 4.33,
    "high60": 6264,
    "drawdown_high": -0.0163,
    "avgVol20": 5296020,
    "avgTurnover20": 30619469232,
    "liquidityFilter": true,
    "blackoutBuy": false,
    "signal": "NONE",
    "label": "",
    "reason": []
  }
}